[
  {
    "id": "14Bd_XWDyAQLUkVnykjgbkhtVODw3qWDr",
    "name": "0101 Caydee Blue Corp",
    "mimeType": "application/vnd.google-apps.folder",
    "parents": ["1JzuKxFekdZx1X_2J6RZx7USp3NsAoWwg"],
    "modifiedTime": "2025-11-11T05:02:16.008Z"
  },
  {
    "id": "1IHdSIBGm14CtP13tdu0EDgU4Q9Rfiycb",
    "name": "2015",
    "mimeType": "application/vnd.google-apps.folder",
    "parents": ["1JzuKxFekdZx1X_2J6RZx7USp3NsAoWwg"],
    "modifiedTime": "2025-11-11T05:02:16.001Z"
  },
  {
    "id": "1j4GeiMCX6URUuHMyAFbznuBfy8o0JJe6",
    "name": "2016 Renewal",
    "mimeType": "application/vnd.google-apps.folder",
    "parents": ["1JzuKxFekdZx1X_2J6RZx7USp3NsAoWwg"],
    "modifiedTime": "2025-11-11T05:02:17.710Z"
  },
  {
    "id": "1Xw9um5Q2NCK74MrNr33-DuWWpBv7h44-",
    "name": "2018",
    "mimeType": "application/vnd.google-apps.folder",
    "parents": ["1JzuKxFekdZx1X_2J6RZx7USp3NsAoWwg"],
    "modifiedTime": "2025-11-11T05:02:17.665Z"
  },
  {
    "id": "1RBfudiV4R7_4dIkzHp_Q0STaTVb1tvOO",
    "name": "2019",
    "mimeType": "application/vnd.google-apps.folder",
    "parents": ["1JzuKxFekdZx1X_2J6RZx7USp3NsAoWwg"],
    "modifiedTime": "2025-11-11T05:02:16.034Z"
  },
  {
    "id": "1P-9YML9xMSGbNf8w8U2hhdL5kWgxR4oj",
    "name": "2020",
    "mimeType": "application/vnd.google-apps.folder",
    "parents": ["1JzuKxFekdZx1X_2J6RZx7USp3NsAoWwg"],
    "modifiedTime": "2025-11-11T05:02:16.268Z"
  },
  {
    "id": "1MTaVC3qpjBeOMhl2Nb971bGqKo9FTMRe",
    "name": "2021",
    "mimeType": "application/vnd.google-apps.folder",
    "parents": ["1JzuKxFekdZx1X_2J6RZx7USp3NsAoWwg"],
    "modifiedTime": "2025-11-11T05:02:16.049Z"
  },
  {
    "id": "1oxz67OtEBbEMEYysuSh8_7gbFEga0GD5",
    "name": "2022",
    "mimeType": "application/vnd.google-apps.folder",
    "parents": ["1JzuKxFekdZx1X_2J6RZx7USp3NsAoWwg"],
    "modifiedTime": "2025-11-11T05:02:16.034Z"
  },
  {
    "id": "1XySuT10zDR1t05F2aEE0eSC4nJd5ZPT-",
    "name": "2023",
    "mimeType": "application/vnd.google-apps.folder",
    "parents": ["1JzuKxFekdZx1X_2J6RZx7USp3NsAoWwg"],
    "modifiedTime": "2025-11-11T05:02:16.041Z"
  },
  {
    "id": "1tA7FgSDNK8raui4PJ5tBjBCD-j9WWKMs",
    "name": "2024",
    "mimeType": "application/vnd.google-apps.folder",
    "parents": ["1JzuKxFekdZx1X_2J6RZx7USp3NsAoWwg"],
    "modifiedTime": "2025-11-11T05:02:15.987Z"
  },
  {
    "id": "197-0sOXGUrf-LeEuRNyLfsXm2zUNj9Tr",
    "name": "2025",
    "mimeType": "application/vnd.google-apps.folder",
    "parents": ["1JzuKxFekdZx1X_2J6RZx7USp3NsAoWwg"],
    "modifiedTime": "2025-11-11T05:02:15.990Z"
  },
  {
    "id": "1vgW1JSCH2GCIBCo_x7ee06WOt3Ax-niq",
    "name": "2025 PKG Cross Sell",
    "mimeType": "application/vnd.google-apps.folder",
    "parents": ["17sB4t2JgC623TBz98pVjIdMOsORHOcl9"],
    "modifiedTime": "2025-11-11T05:02:19.110Z"
  },
  {
    "id": "1rBzU1qv7vaRoWit72SrygtxMf0sCwDKQ",
    "name": "2025 PKG Cross Sell",
    "mimeType": "application/vnd.google-apps.folder",
    "parents": ["1Mw76Pd1m03Is-2ie1e6ydRXMOYinWWNL"],
    "modifiedTime": "2025-11-11T05:02:18.976Z"
  },
  {
    "id": "1cPGOHpydoFGZ2I-EpyBeactB4qeU9E3X",
    "name": "2025 WC Renewal",
    "mimeType": "application/vnd.google-apps.folder",
    "parents": ["1Mw76Pd1m03Is-2ie1e6ydRXMOYinWWNL"],
    "modifiedTime": "2025-11-11T05:02:18.969Z"
  },
  {
    "id": "1vkpWzCWQMhRQt2ewRZwqpe5XP_PNBTN7",
    "name": "2026",
    "mimeType": "application/vnd.google-apps.folder",
    "parents": ["1JzuKxFekdZx1X_2J6RZx7USp3NsAoWwg"],
    "modifiedTime": "2025-11-11T05:05:32.951Z"
  },
  {
    "id": "11k30zZgy76477bx2CPpG8uV01KX-xBuk",
    "name": "2026",
    "mimeType": "application/vnd.google-apps.folder",
    "parents": ["1JzuKxFekdZx1X_2J6RZx7USp3NsAoWwg"],
    "modifiedTime": "2025-11-11T05:02:16.046Z"
  },
  {
    "id": "1Ip905CNeAv4xdnSeikkjLH2B8E-I_S82",
    "name": "2026 WC",
    "mimeType": "application/vnd.google-apps.folder",
    "parents": ["1vkpWzCWQMhRQt2ewRZwqpe5XP_PNBTN7"],
    "modifiedTime": "2025-11-11T05:02:17.709Z"
  },
  {
    "id": "1mFIf_Gq2yPlJw5OnEl1VKbcjxjSWaxlE",
    "name": "2026 WC Renewal",
    "mimeType": "application/vnd.google-apps.folder",
    "parents": ["1Ip905CNeAv4xdnSeikkjLH2B8E-I_S82"],
    "modifiedTime": "2025-11-11T05:02:20.584Z"
  },
  {
    "id": "1X9wqyI8F70DTH6osAg75oXcuiXBFj0Op",
    "name": "2026 WC Renewal",
    "mimeType": "application/vnd.google-apps.folder",
    "parents": ["17sB4t2JgC623TBz98pVjIdMOsORHOcl9"],
    "modifiedTime": "2025-11-11T05:02:19.060Z"
  },
  {
    "id": "1au5VXAbS4dqPSczDoyQtsSTdobyHNhMt",
    "name": "Billing, Audit & Cancellations",
    "mimeType": "application/vnd.google-apps.folder",
    "parents": ["17sB4t2JgC623TBz98pVjIdMOsORHOcl9"],
    "modifiedTime": "2025-11-11T05:02:19.074Z"
  },
  {
    "id": "1OBjuJXh4GbQN0Tyhyl8xYkvNvYzWj3P8",
    "name": "Billing, Audit & Cancellations",
    "mimeType": "application/vnd.google-apps.folder",
    "parents": ["1Mw76Pd1m03Is-2ie1e6ydRXMOYinWWNL"],
    "modifiedTime": "2025-11-11T05:02:18.959Z"
  },
  {
    "id": "1Ew5OnDfrogRwqrPWjsZaseCjeujLhuJw",
    "name": "Billing, Audit, & Cancellations",
    "mimeType": "application/vnd.google-apps.folder",
    "parents": ["1Ip905CNeAv4xdnSeikkjLH2B8E-I_S82"],
    "modifiedTime": "2025-11-11T05:02:20.630Z"
  },
  {
    "id": "1JzuKxFekdZx1X_2J6RZx7USp3NsAoWwg",
    "name": "Caydee Blue Corp. dba Right at Home",
    "mimeType": "application/vnd.google-apps.folder",
    "parents": ["0AOulfXIJNYOzUk9PVA"],
    "modifiedTime": "2025-11-11T05:02:14.560Z"
  },
  {
    "id": "1Ncef06KmQC0FJS2iN6x4rvCYcpnaXMt-",
    "name": "Claims",
    "mimeType": "application/vnd.google-apps.folder",
    "parents": ["1Ip905CNeAv4xdnSeikkjLH2B8E-I_S82"],
    "modifiedTime": "2025-11-11T05:02:20.635Z"
  },
  {
    "id": "1oq024O-IdylTomn5JWqF5Ym75d7par57",
    "name": "Claims",
    "mimeType": "application/vnd.google-apps.folder",
    "parents": ["17sB4t2JgC623TBz98pVjIdMOsORHOcl9"],
    "modifiedTime": "2025-11-11T05:02:19.102Z"
  },
  {
    "id": "1vcYdcHQqo4k8ufgQ4k4JUBnoYUmxkLDM",
    "name": "Claims",
    "mimeType": "application/vnd.google-apps.folder",
    "parents": ["1Mw76Pd1m03Is-2ie1e6ydRXMOYinWWNL"],
    "modifiedTime": "2025-11-11T05:02:19.019Z"
  },
  {
    "id": "1ihv9Bw3OGinapZTan4BtKIbbb5qqzbbC",
    "name": "Policy & Endorsements",
    "mimeType": "application/vnd.google-apps.folder",
    "parents": ["1Ip905CNeAv4xdnSeikkjLH2B8E-I_S82"],
    "modifiedTime": "2025-11-11T05:02:20.635Z"
  },
  {
    "id": "1gQtPYr1iHWss9aCDPtb7uH9RZkxz44mR",
    "name": "Policy & Endorsements",
    "mimeType": "application/vnd.google-apps.folder",
    "parents": ["17sB4t2JgC623TBz98pVjIdMOsORHOcl9"],
    "modifiedTime": "2025-11-11T05:02:19.111Z"
  },
  {
    "id": "1Iq5v_XOKLs5ep2UT3doeqv11-Fr3JDDD",
    "name": "Policy & Endorsements",
    "mimeType": "application/vnd.google-apps.folder",
    "parents": ["1Mw76Pd1m03Is-2ie1e6ydRXMOYinWWNL"],
    "modifiedTime": "2025-11-11T05:02:18.961Z"
  },
  {
    "id": "17sB4t2JgC623TBz98pVjIdMOsORHOcl9",
    "name": "WC",
    "mimeType": "application/vnd.google-apps.folder",
    "parents": ["11k30zZgy76477bx2CPpG8uV01KX-xBuk"],
    "modifiedTime": "2025-11-11T05:02:17.712Z"
  },
  {
    "id": "1Mw76Pd1m03Is-2ie1e6ydRXMOYinWWNL",
    "name": "WC",
    "mimeType": "application/vnd.google-apps.folder",
    "parents": ["197-0sOXGUrf-LeEuRNyLfsXm2zUNj9Tr"],
    "modifiedTime": "2025-11-11T05:02:17.709Z"
  }
]
